scipy_pilutil/__init__.py
scipy_pilutil/pilutil.py
scipy_pilutil/patch/__init__.py
scipy_pilutil-0.2.1.dist-info/LICENSE
scipy_pilutil-0.2.1.dist-info/METADATA
scipy_pilutil-0.2.1.dist-info/WHEEL
scipy_pilutil-0.2.1.dist-info/top_level.txt
scipy_pilutil-0.2.1.dist-info/RECORD
