Metadata-Version: 2.1
Name: scipy-pilutil
Version: 0.2.1
Summary: scipy.misc.pilutil module for legacy code
Home-page: http://github.com/kairi003/scipy_pilutil
Author: kairi
Author-email: kairi.satellite@gmail.com
License: BSD-3-Clause
License-File: LICENSE
Requires-Dist: numpy
Requires-Dist: Pillow
